{
  "title": "Chrome Languages Toggle",
  "rules": [
    {
      "description": "right click, cursor down, enter, language change",
      "manipulators": [
        {
          "type": "basic",
          "from": {
            "key_code": "l",
            "modifiers": {
              "mandatory": ["left_control"]
            }
          },
          "to": [
            { "pointing_button": "button2" }
          ],
          "to_after_key_up": [
            { "key_code": "t", "halt": true, "delay_milliseconds": 100 }
          ]
        }
      ]
    }
  ]
}
